MANIFEST.in
README.md
setup.py
src/tunneller/__init__.py
src/tunneller/cluster.ini
src/tunneller/tunnel.py
src/tunneller.egg-info/PKG-INFO
src/tunneller.egg-info/SOURCES.txt
src/tunneller.egg-info/dependency_links.txt
src/tunneller.egg-info/entry_points.txt
src/tunneller.egg-info/top_level.txt