Metadata-Version: 2.1
Name: tunneller
Version: 0.1.6
Summary: Utility to manage SSH-Tunnel to CINECA clusters
Home-page: https://github.com/so07/tunneller
Author: Sergio Orlandini
Author-email: s.orlandini@cineca.it
License: UNKNOWN
Platform: UNKNOWN
Classifier: Programming Language :: Python :: 3
Classifier: License :: OSI Approved :: MIT License
